api_vendo/__init__.py
api_vendo/api_vendo.py
api_vendo-1.0.1.dist-info/LICENSE
api_vendo-1.0.1.dist-info/METADATA
api_vendo-1.0.1.dist-info/WHEEL
api_vendo-1.0.1.dist-info/top_level.txt
api_vendo-1.0.1.dist-info/RECORD
