Metadata-Version: 2.1
Name: api-vendo
Version: 1.0.1
Summary: Support script for Vendo API connection
Home-page: https://github.com/asgard-sp-z-o-o/api_vendo
Author: Robert Lewandowski
Author-email: r.lewandowski@asgard.gifts
License: UNKNOWN
Platform: UNKNOWN
Classifier: Programming Language :: Python :: 3
Classifier: License :: OSI Approved :: MIT License
Classifier: Operating System :: OS Independent
Requires-Python: >=3.6
